mxmul_pkgh/__init__.py
mxmul_pkgh/mxmul.py
mxmul-0.1.0.dist-info/LICENSE
mxmul-0.1.0.dist-info/METADATA
mxmul-0.1.0.dist-info/WHEEL
mxmul-0.1.0.dist-info/top_level.txt
mxmul-0.1.0.dist-info/RECORD
