Metadata-Version: 2.1
Name: mxmul
Version: 0.1.0
Summary: new learner
Home-page: https://pypi.org/
Author: suiyi
Author-email: h2838443896@163.com
License: License
Platform: UNKNOWN
Classifier: Programming Language :: Python :: 3
Classifier: License :: OSI Approved :: MIT License
Classifier: Operating System :: OS Independent
